GeoCS/__init__.py
GeoCS/calc_lib.py
GeoCS/data_lib.py
GeoCS/plot_lib.py
GeoCS/.ipynb_checkpoints/__init__-checkpoint.py
GeoCS/.ipynb_checkpoints/calc_lib-checkpoint.py
GeoCS/.ipynb_checkpoints/data_lib-checkpoint.py
GeoCS/.ipynb_checkpoints/plot_lib-checkpoint.py
geocs-1.0.3.dist-info/METADATA
geocs-1.0.3.dist-info/WHEEL
geocs-1.0.3.dist-info/licenses/LICENSE.txt
geocs-1.0.3.dist-info/RECORD
